README.md
setup.py
dev_w.egg-info/PKG-INFO
dev_w.egg-info/SOURCES.txt
dev_w.egg-info/dependency_links.txt
dev_w.egg-info/entry_points.txt
dev_w.egg-info/namespace_packages.txt
dev_w.egg-info/requires.txt
dev_w.egg-info/top_level.txt
orangecontrib/__init__.py
orangecontrib/dev_workflow/__init__.py
orangecontrib/dev_workflow/widgets/Chatbot.py
orangecontrib/dev_workflow/widgets/MetManagement.py
orangecontrib/dev_workflow/widgets/VarManagement.py
orangecontrib/dev_workflow/widgets/WrapMessageBox.py
orangecontrib/dev_workflow/widgets/__init__.py
orangecontrib/dev_workflow/widgets/goto.py
orangecontrib/dev_workflow/widgets/orange_sub_workflow.py
orangecontrib/dev_workflow/widgets/shared_functions.py
orangecontrib/dev_workflow/widgets/shared_variables.py
orangecontrib/dev_workflow/widgets/subworkflow_input.py
orangecontrib/dev_workflow/widgets/subworkflow_output.py
orangecontrib/dev_workflow/widgets/icons/Emblem_of_Napoleon_Bonaparte.svg
orangecontrib/dev_workflow/widgets/icons/Logo_HKH.svg
orangecontrib/dev_workflow/widgets/icons/Logo_HKH_4.svg
orangecontrib/dev_workflow/widgets/icons/Logo_HKH_4_jc.svg
orangecontrib/dev_workflow/widgets/icons/Napoleon2.svg
orangecontrib/dev_workflow/widgets/icons/Pikachu SVG File.svg
orangecontrib/dev_workflow/widgets/icons/Workflow.svg
orangecontrib/dev_workflow/widgets/icons/category.svg
orangecontrib/dev_workflow/widgets/icons/database.svg
orangecontrib/dev_workflow/widgets/icons/download-svgrepo-com.svg
orangecontrib/dev_workflow/widgets/icons/ecriture.svg
orangecontrib/dev_workflow/widgets/icons/file-transfer.png
orangecontrib/dev_workflow/widgets/icons/goto.png
orangecontrib/dev_workflow/widgets/icons/goto.svg
orangecontrib/dev_workflow/widgets/icons/icon_surrogate_learner.png
orangecontrib/dev_workflow/widgets/icons/icon_surrogate_predict.png
orangecontrib/dev_workflow/widgets/icons/input.png
orangecontrib/dev_workflow/widgets/icons/interrupteur.svg
orangecontrib/dev_workflow/widgets/icons/jcm_export_score.png
orangecontrib/dev_workflow/widgets/icons/jcm_open_file_resize_alpha_channel.png
orangecontrib/dev_workflow/widgets/icons/jcm_optuna_parameters_setting.png
orangecontrib/dev_workflow/widgets/icons/jcm_output_table.png
